ckanext_ark-1.0.4-py3.10-nspkg.pth
ckanext/ark/__init__.py
ckanext/ark/cli.py
ckanext/ark/plugin.py
ckanext/ark/views.py
ckanext/ark/i18n/zh_Hant_TW/LC_MESSAGES/ckanext-ark.mo
ckanext/ark/lib/__init__.py
ckanext/ark/lib/helpers.py
ckanext/ark/lib/minter.py
ckanext/ark/model/__init__.py
ckanext/ark/model/ark.py
ckanext/ark/model/crud.py
ckanext/ark/templates/ark/snippets/ark.html
ckanext/ark/templates/ark/snippets/defunct.html
ckanext_ark-1.0.4.dist-info/licenses/LICENSE
ckanext_ark-1.0.4.dist-info/METADATA
ckanext_ark-1.0.4.dist-info/WHEEL
ckanext_ark-1.0.4.dist-info/entry_points.txt
ckanext_ark-1.0.4.dist-info/namespace_packages.txt
ckanext_ark-1.0.4.dist-info/top_level.txt
ckanext_ark-1.0.4.dist-info/RECORD
