Metadata-Version: 2.4
Name: ckanext-ark
Version: 1.0.4
Summary: A CKAN extension for assigning Archival Resource Key (ARK) identifiers to datasets.
Home-page: https://github.com/depositar/ckanext-ark
Author: Cheng-Jen Lee
Author-email: u103133.u103135@gmail.com
License: MIT
Keywords: CKAN ARK
Classifier: License :: OSI Approved :: MIT License
Classifier: Programming Language :: Python :: 3.8
Classifier: Programming Language :: Python :: 3.9
Classifier: Programming Language :: Python :: 3.10
License-File: LICENSE
Requires-Dist: ckantoolkit
Requires-Dist: noid-mint
Dynamic: author
Dynamic: author-email
Dynamic: classifier
Dynamic: description
Dynamic: description-content-type
Dynamic: home-page
Dynamic: keywords
Dynamic: license
Dynamic: license-file
Dynamic: requires-dist
Dynamic: summary
